obscura.py
obscura-0.1.1.dist-info/METADATA
obscura-0.1.1.dist-info/WHEEL
obscura-0.1.1.dist-info/entry_points.txt
obscura-0.1.1.dist-info/licenses/LICENSE.md
obscura-0.1.1.dist-info/RECORD
